py3Settings/__init__.py
py3Settings/file.py
py3Settings/main.py
py3Settings/proxy.py
py3Settings/utils.py
py3Settings/modules/__init__.py
py3Settings/modules/attributes.py
py3settings-3.3.7.dist-info/LICENSE
py3settings-3.3.7.dist-info/METADATA
py3settings-3.3.7.dist-info/WHEEL
py3settings-3.3.7.dist-info/top_level.txt
py3settings-3.3.7.dist-info/RECORD
