Metadata-Version: 2.1
Name: py3settings
Version: 3.3.7
Summary: A powerful json file settings manager for Python 3
Home-page: https://github.com/acalasanzs/py3Settings
Author: Albert Calasanz Sallen
Author-email: acalasanzs@gmail.com
Project-URL: Bug Tracker, https://github.com/acalasanzs/py3Settings/issues
Classifier: Programming Language :: Python :: 3
Classifier: License :: OSI Approved :: MIT License
Classifier: Operating System :: OS Independent
Requires-Python: >=3.6
License-File: LICENSE
